rtl/riscv_alu.sv
module riscv_alu (
    input  logic [31:0] a,
    input  logic [31:0] b,
    input  logic [3:0]  alu_op,
    output logic [31:0] result,
    output logic        zero
);

    localparam ALU_ADD = 4'd0;
    localparam ALU_SUB = 4'd1;
    localparam ALU_AND = 4'd2;
    localparam ALU_OR  = 4'd3;
    localparam ALU_XOR = 4'd4;
    localparam ALU_SLL = 4'd5;
    localparam ALU_SRL = 4'd6;
    localparam ALU_SRA = 4'd7;
    localparam ALU_SLT = 4'd8;
    localparam ALU_SLTU = 4'd9;

    always_comb begin
        case (alu_op)
            ALU_ADD:  result = a + b;
            ALU_SUB:  result = a - b;
            ALU_AND:  result = a & b;
            ALU_OR:   result = a | b;
            ALU_XOR:  result = a ^ b;
            ALU_SLL:  result = a << b[4:0];
            ALU_SRL:  result = a >> b[4:0];
            ALU_SRA:  result = $signed(a) >>> b[4:0];
            ALU_SLT:  result = ($signed(a) < $signed(b)) ? 32'd1 : 32'd0;
            ALU_SLTU: result = (a < b) ? 32'd1 : 32'd0;
            default:  result = 32'd0;
        endcase
    end

    assign zero = (result == 32'd0);

endmodule

tb/tb_alu.sv
`timescale 1ns/1ps

module tb_alu;

    logic [31:0] a;
    logic [31:0] b;
    logic [3:0]  alu_op;
    logic [31:0] result;
    logic        zero;

    int tests_passed = 0;
    int tests_failed = 0;

    riscv_alu dut (
        .a(a),
        .b(b),
        .alu_op(alu_op),
        .result(result),
        .zero(zero)
    );

    task check(
        input [31:0] test_a,
        input [31:0] test_b,
        input [3:0]  test_op,
        input [31:0] expected,
        input string test_name
    );
        begin
            a = test_a;
            b = test_b;
            alu_op = test_op;
            #1;

            if (result === expected) begin
                $display("[PASS] %s", test_name);
                tests_passed++;
            end else begin
                $display("[FAIL] %s | a=%h b=%h op=%0d expected=%h got=%h",
                         test_name, a, b, alu_op, expected, result);
                tests_failed++;
            end
        end
    endtask

    initial begin
        $dumpfile("waves/alu.vcd");
        $dumpvars(0, tb_alu);

        $display("Starting RISC-V ALU verification...");

        check(32'd10, 32'd5,  4'd0, 32'd15, "ADD basic");
        check(32'd10, 32'd5,  4'd1, 32'd5,  "SUB basic");
        check(32'hF0F0, 32'h0FF0, 4'd2, 32'h00F0, "AND basic");
        check(32'hF0F0, 32'h0FF0, 4'd3, 32'hFFF0, "OR basic");
        check(32'hAAAA, 32'h5555, 4'd4, 32'hFFFF, "XOR basic");

        check(32'd1, 32'd4, 4'd5, 32'd16, "SLL shift left");
        check(32'd16, 32'd2, 4'd6, 32'd4, "SRL shift right");
        check(32'h80000000, 32'd4, 4'd7, 32'hF8000000, "SRA arithmetic shift");

        check(32'd3, 32'd7, 4'd8, 32'd1, "SLT signed true");
        check(32'd7, 32'd3, 4'd8, 32'd0, "SLT signed false");
        check(32'hFFFFFFFF, 32'd1, 4'd9, 32'd0, "SLTU unsigned false");

        check(32'd5, 32'd5, 4'd1, 32'd0, "ZERO flag case");

        if (zero !== 1'b1) begin
            $display("[FAIL] zero flag should be 1");
            tests_failed++;
        end else begin
            $display("[PASS] zero flag works");
            tests_passed++;
        end

        $display("--------------------------------");
        $display("Tests passed: %0d", tests_passed);
        $display("Tests failed: %0d", tests_failed);
        $display("--------------------------------");

        if (tests_failed == 0)
            $display("ALU VERIFICATION PASSED");
        else
            $display("ALU VERIFICATION FAILED");

        $finish;
    end

endmodule

waves/alu.vcd
$date
	Thu May 14 23:21:42 2026
$end
$version
	Icarus Verilog
$end
$timescale
	1ps
$end
$scope module tb_alu $end
$var wire 1 ! zero $end
$var wire 32 " result [31:0] $end
$var reg 32 # a [31:0] $end
$var reg 4 $ alu_op [3:0] $end
$var reg 32 % b [31:0] $end
$var integer 32 & tests_failed [31:0] $end
$var integer 32 ' tests_passed [31:0] $end
$scope module dut $end
$var wire 32 ( a [31:0] $end
$var wire 4 ) alu_op [3:0] $end
$var wire 32 * b [31:0] $end
$var wire 1 ! zero $end
$var parameter 4 + ALU_ADD $end
$var parameter 4 , ALU_AND $end
$var parameter 4 - ALU_OR $end
$var parameter 4 . ALU_SLL $end
$var parameter 4 / ALU_SLT $end
$var parameter 4 0 ALU_SLTU $end
$var parameter 4 1 ALU_SRA $end
$var parameter 4 2 ALU_SRL $end
$var parameter 4 3 ALU_SUB $end
$var parameter 4 4 ALU_XOR $end
$var reg 32 5 result [31:0] $end
$upscope $end
$scope task check $end
$var reg 32 6 expected [31:0] $end
$var reg 32 7 test_a [31:0] $end
$var reg 32 8 test_b [31:0] $end
$var reg 4 9 test_op [3:0] $end
$upscope $end
$upscope $end
$enddefinitions $end
$comment Show the parameter values. $end
$dumpall
b100 4
b1 3
b110 2
b111 1
b1001 0
b1000 /
b101 .
b11 -
b10 ,
b0 +
$end
#0
$dumpvars
b0 9
b101 8
b1010 7
b1111 6
b1111 5
b101 *
b0 )
b1010 (
b0 '
b0 &
b101 %
b0 $
b1010 #
b1111 "
0!
$end
#1000
b101 "
b101 5
b1 $
b1 )
b101 6
b1 9
b1 '
#2000
b11110000 "
b11110000 5
b10 $
b10 )
b111111110000 %
b111111110000 *
b1111000011110000 #
b1111000011110000 (
b11110000 6
b10 9
b111111110000 8
b1111000011110000 7
b10 '
#3000
b1111111111110000 "
b1111111111110000 5
b11 $
b11 )
b1111111111110000 6
b11 9
b11 '
#4000
b1111111111111111 "
b1111111111111111 5
b100 $
b100 )
b101010101010101 %
b101010101010101 *
b1010101010101010 #
b1010101010101010 (
b1111111111111111 6
b100 9
b101010101010101 8
b1010101010101010 7
b100 '
#5000
b10000 "
b10000 5
b101 $
b101 )
b100 %
b100 *
b1 #
b1 (
b10000 6
b101 9
b100 8
b1 7
b101 '
#6000
b100 "
b100 5
b110 $
b110 )
b10 %
b10 *
b10000 #
b10000 (
b100 6
b110 9
b10 8
b10000 7
b110 '
#7000
b11111000000000000000000000000000 "
b11111000000000000000000000000000 5
b111 $
b111 )
b100 %
b100 *
b10000000000000000000000000000000 #
b10000000000000000000000000000000 (
b11111000000000000000000000000000 6
b111 9
b100 8
b10000000000000000000000000000000 7
b111 '
#8000
b1 "
b1 5
b1000 $
b1000 )
b111 %
b111 *
b11 #
b11 (
b1 6
b1000 9
b111 8
b11 7
b1000 '
#9000
1!
b0 "
b0 5
b11 %
b11 *
b111 #
b111 (
b0 6
b11 8
b111 7
b1001 '
#10000
b1001 $
b1001 )
b1 %
b1 *
b11111111111111111111111111111111 #
b11111111111111111111111111111111 (
b1001 9
b1 8
b11111111111111111111111111111111 7
b1010 '
#11000
b1 $
b1 )
b101 %
b101 *
b101 #
b101 (
b1 9
b101 8
b101 7
b1011 '
#12000
b1101 '
