rtl/riscv_alu.sv
module riscv_alu (
    input  logic [31:0] a,
    input  logic [31:0] b,
    input  logic [3:0]  alu_op,
    output logic [31:0] result,
    output logic        zero
);

    localparam ALU_ADD = 4'd0;
    localparam ALU_SUB = 4'd1;
    localparam ALU_AND = 4'd2;
    localparam ALU_OR  = 4'd3;
    localparam ALU_XOR = 4'd4;
    localparam ALU_SLL = 4'd5;
    localparam ALU_SRL = 4'd6;
    localparam ALU_SRA = 4'd7;
    localparam ALU_SLT = 4'd8;
    localparam ALU_SLTU = 4'd9;

    always_comb begin
        case (alu_op)
            ALU_ADD:  result = a + b;
            ALU_SUB:  result = a - b;
            ALU_AND:  result = a & b;
            ALU_OR:   result = a | b;
            ALU_XOR:  result = a ^ b;
            ALU_SLL:  result = a << b[4:0];
            ALU_SRL:  result = a >> b[4:0];
            ALU_SRA:  result = $signed(a) >>> b[4:0];
            ALU_SLT:  result = ($signed(a) < $signed(b)) ? 32'd1 : 32'd0;
            ALU_SLTU: result = (a < b) ? 32'd1 : 32'd0;
            default:  result = 32'd0;
        endcase
    end

    assign zero = (result == 32'd0);

endmodule

tb/tb_alu.sv
`timescale 1ns/1ps

module tb_alu;

    logic [31:0] a;
    logic [31:0] b;
    logic [3:0]  alu_op;
    logic [31:0] result;
    logic        zero;

    int tests_passed = 0;
    int tests_failed = 0;

    riscv_alu dut (
        .a(a),
        .b(b),
        .alu_op(alu_op),
        .result(result),
        .zero(zero)
    );

    task check(
        input [31:0] test_a,
        input [31:0] test_b,
        input [3:0]  test_op,
        input [31:0] expected,
        input string test_name
    );
        begin
            a = test_a;
            b = test_b;
            alu_op = test_op;
            #1;

            if (result === expected) begin
                $display("[PASS] %s", test_name);
                tests_passed++;
            end else begin
                $display("[FAIL] %s | a=%h b=%h op=%0d expected=%h got=%h",
                         test_name, a, b, alu_op, expected, result);
                tests_failed++;
            end
        end
    endtask

    initial begin
        $dumpfile("waves/alu.vcd");
        $dumpvars(0, tb_alu);

        $display("Starting RISC-V ALU verification...");

        // Directed tests
        check(32'd10, 32'd5,  4'd0, 32'd15, "ADD basic");
        check(32'd10, 32'd5,  4'd1, 32'd5,  "SUB basic");
        check(32'hF0F0, 32'h0FF0, 4'd2, 32'h00F0, "AND basic");
        check(32'hF0F0, 32'h0FF0, 4'd3, 32'hFFF0, "OR basic");
        check(32'hAAAA, 32'h5555, 4'd4, 32'hFFFF, "XOR basic");

        check(32'd1, 32'd4, 4'd5, 32'd16, "SLL shift left");
        check(32'd16, 32'd2, 4'd6, 32'd4, "SRL shift right");
        check(32'h80000000, 32'd4, 4'd7, 32'hF8000000, "SRA arithmetic shift");

        check(32'd3, 32'd7, 4'd8, 32'd1, "SLT signed true");
        check(32'd7, 32'd3, 4'd8, 32'd0, "SLT signed false");
        check(32'hFFFFFFFF, 32'd1, 4'd9, 32'd0, "SLTU unsigned false");

        check(32'd5, 32'd5, 4'd1, 32'd0, "ZERO flag case");

        if (zero !== 1'b1) begin
            $display("[FAIL] zero flag should be 1");
            tests_failed++;
        end else begin
            $display("[PASS] zero flag works");
            tests_passed++;
        end

        // Randomized tests using golden model
        $display("Starting randomized ALU tests...");

        for (int i = 0; i < 100; i++) begin
            logic [31:0] rand_a;
            logic [31:0] rand_b;
            logic [3:0]  rand_op;
            logic [31:0] expected;

            rand_a = $urandom;
            rand_b = $urandom;
            rand_op = $urandom_range(0, 9);

            case (rand_op)
                4'd0: expected = rand_a + rand_b;
                4'd1: expected = rand_a - rand_b;
                4'd2: expected = rand_a & rand_b;
                4'd3: expected = rand_a | rand_b;
                4'd4: expected = rand_a ^ rand_b;
                4'd5: expected = rand_a << rand_b[4:0];
                4'd6: expected = rand_a >> rand_b[4:0];
                4'd7: expected = $signed(rand_a) >>> rand_b[4:0];
                4'd8: expected = ($signed(rand_a) < $signed(rand_b)) ? 32'd1 : 32'd0;
                4'd9: expected = (rand_a < rand_b) ? 32'd1 : 32'd0;
                default: expected = 32'd0;
            endcase

            check(rand_a, rand_b, rand_op, expected, "Random ALU test");
        end

        $display("--------------------------------");
        $display("Tests passed: %0d", tests_passed);
        $display("Tests failed: %0d", tests_failed);
        $display("--------------------------------");

        if (tests_failed == 0)
            $display("ALU VERIFICATION PASSED");
        else
            $display("ALU VERIFICATION FAILED");

        $finish;
    end

endmodule

waves/alu.vcd
$date
	Fri May 15 21:01:23 2026
$end
$version
	Icarus Verilog
$end
$timescale
	1ps
$end
$scope module tb_alu $end
$var wire 1 ! zero $end
$var wire 32 " result [31:0] $end
$var reg 32 # a [31:0] $end
$var reg 4 $ alu_op [3:0] $end
$var reg 32 % b [31:0] $end
$var integer 32 & tests_failed [31:0] $end
$var integer 32 ' tests_passed [31:0] $end
$scope module dut $end
$var wire 32 ( a [31:0] $end
$var wire 4 ) alu_op [3:0] $end
$var wire 32 * b [31:0] $end
$var wire 1 ! zero $end
$var parameter 4 + ALU_ADD $end
$var parameter 4 , ALU_AND $end
$var parameter 4 - ALU_OR $end
$var parameter 4 . ALU_SLL $end
$var parameter 4 / ALU_SLT $end
$var parameter 4 0 ALU_SLTU $end
$var parameter 4 1 ALU_SRA $end
$var parameter 4 2 ALU_SRL $end
$var parameter 4 3 ALU_SUB $end
$var parameter 4 4 ALU_XOR $end
$var reg 32 5 result [31:0] $end
$upscope $end
$scope begin $ivl_for_loop0 $end
$var integer 32 6 i [31:0] $end
$scope begin $unm_blk_8 $end
$var reg 32 7 expected [31:0] $end
$var reg 32 8 rand_a [31:0] $end
$var reg 32 9 rand_b [31:0] $end
$var reg 4 : rand_op [3:0] $end
$upscope $end
$upscope $end
$scope task check $end
$var reg 32 ; expected [31:0] $end
$var reg 32 < test_a [31:0] $end
$var reg 32 = test_b [31:0] $end
$var reg 4 > test_op [3:0] $end
$upscope $end
$upscope $end
$enddefinitions $end
$comment Show the parameter values. $end
$dumpall
b100 4
b1 3
b110 2
b111 1
b1001 0
b1000 /
b101 .
b11 -
b10 ,
b0 +
$end
#0
$dumpvars
b0 >
b101 =
b1010 <
b1111 ;
bx :
bx 9
bx 8
bx 7
b0 6
b1111 5
b101 *
b0 )
b1010 (
b0 '
b0 &
b101 %
b0 $
b1010 #
b1111 "
0!
$end
#1000
b101 "
b101 5
b1 $
b1 )
b101 ;
b1 >
b1 '
#2000
b11110000 "
b11110000 5
b10 $
b10 )
b111111110000 %
b111111110000 *
b1111000011110000 #
b1111000011110000 (
b11110000 ;
b10 >
b111111110000 =
b1111000011110000 <
b10 '
#3000
b1111111111110000 "
b1111111111110000 5
b11 $
b11 )
b1111111111110000 ;
b11 >
b11 '
#4000
b1111111111111111 "
b1111111111111111 5
b100 $
b100 )
b101010101010101 %
b101010101010101 *
b1010101010101010 #
b1010101010101010 (
b1111111111111111 ;
b100 >
b101010101010101 =
b1010101010101010 <
b100 '
#5000
b10000 "
b10000 5
b101 $
b101 )
b100 %
b100 *
b1 #
b1 (
b10000 ;
b101 >
b100 =
b1 <
b101 '
#6000
b100 "
b100 5
b110 $
b110 )
b10 %
b10 *
b10000 #
b10000 (
b100 ;
b110 >
b10 =
b10000 <
b110 '
#7000
b11111000000000000000000000000000 "
b11111000000000000000000000000000 5
b111 $
b111 )
b100 %
b100 *
b10000000000000000000000000000000 #
b10000000000000000000000000000000 (
b11111000000000000000000000000000 ;
b111 >
b100 =
b10000000000000000000000000000000 <
b111 '
#8000
b1 "
b1 5
b1000 $
b1000 )
b111 %
b111 *
b11 #
b11 (
b1 ;
b1000 >
b111 =
b11 <
b1000 '
#9000
1!
b0 "
b0 5
b11 %
b11 *
b111 #
b111 (
b0 ;
b11 =
b111 <
b1001 '
#10000
b1001 $
b1001 )
b1 %
b1 *
b11111111111111111111111111111111 #
b11111111111111111111111111111111 (
b1001 >
b1 =
b11111111111111111111111111111111 <
b1010 '
#11000
b1 $
b1 )
b101 %
b101 *
b101 #
b101 (
b1 >
b101 =
b101 <
b1011 '
#12000
0!
b11010010100111101001001110100101 "
b11010010100111101001001110100101 5
b0 $
b0 )
b1000000100010010101111010000001 %
b1000000100010010101111010000001 *
b10010010000101010011010100100100 #
b10010010000101010011010100100100 (
b11010010100111101001001110100101 ;
b0 >
b1000000100010010101111010000001 =
b10010010000101010011010100100100 <
b11010010100111101001001110100101 7
b0 :
b1000000100010010101111010000001 9
b10010010000101010011010100100100 8
b1101 '
#13000
b11000111110000010 "
b11000111110000010 5
b111 $
b111 )
b10000110101110010111101100001101 %
b10000110101110010111101100001101 *
b110001111100000101011001100011 #
b110001111100000101011001100011 (
b11000111110000010 ;
b111 >
b10000110101110010111101100001101 =
b110001111100000101011001100011 <
b11000111110000010 7
b111 :
b10000110101110010111101100001101 9
b110001111100000101011001100011 8
b1 6
b1110 '
#14000
b10001100101000000000000000000 "
b10001100101000000000000000000 5
b101 $
b101 )
b1001001101110101001000010010 %
b1001001101110101001000010010 *
b110010110000101000010001100101 #
b110010110000101000010001100101 (
b10001100101000000000000000000 ;
b101 >
b1001001101110101001000010010 =
b110010110000101000010001100101 <
b10001100101000000000000000000 7
b101 :
b1001001101110101001000010010 9
b110010110000101000010001100101 8
b10 6
b1111 '
#15000
b1000011011 "
b1000011011 5
b110 $
b110 )
b10111011001000111111000101110110 %
b10111011001000111111000101110110 *
b10000110110101111100110100001101 #
b10000110110101111100110100001101 (
b1000011011 ;
b110 >
b10111011001000111111000101110110 =
b10000110110101111100110100001101 <
b1000011011 7
b110 :
b10111011001000111111000101110110 9
b10000110110101111100110100001101 8
b11 6
b10000 '
#16000
1!
b0 "
b0 5
b1001 $
b1001 )
b11000110001011011111011110001100 %
b11000110001011011111011110001100 *
b11110110110101000101011111101101 #
b11110110110101000101011111101101 (
b0 ;
b1001 >
b11000110001011011111011110001100 =
b11110110110101000101011111101101 <
b0 7
b1001 :
b11000110001011011111011110001100 9
b11110110110101000101011111101101 8
b100 6
b10001 '
#17000
0!
b1100011111101111010010011000111 "
b1100011111101111010010011000111 5
b11 $
b11 )
b1100010111101111000010011000101 %
b1100010111101111000010011000101 *
b1100011001101110010010011000110 #
b1100011001101110010010011000110 (
b1100011111101111010010011000111 ;
b11 >
b1100010111101111000010011000101 =
b1100011001101110010010011000110 <
b1100011111101111010010011000111 7
b11 :
b1100010111101111000010011000101 9
b1100011001101110010010011000110 8
b101 6
b10010 '
#18000
b101110100000100110101001011100 "
b101110100000100110101001011100 5
b0 $
b0 )
b111011110100100111001001110111 %
b111011110100100111001001110111 *
b11110010101011111111011111100101 #
b11110010101011111111011111100101 (
b101110100000100110101001011100 ;
b0 >
b111011110100100111001001110111 =
b11110010101011111111011111100101 <
b101110100000100110101001011100 7
b0 :
b111011110100100111001001110111 9
b11110010101011111111011111100101 8
b110 6
b10011 '
#19000
b111110110111001011001001111101 "
b111110110111001011001001111101 5
b100 $
b100 )
b11111001001100000110100111110010 %
b11111001001100000110100111110010 *
b11000111111011001101101110001111 #
b11000111111011001101101110001111 (
b111110110111001011001001111101 ;
b100 >
b11111001001100000110100111110010 =
b11000111111011001101101110001111 <
b111110110111001011001001111101 7
b100 :
b11111001001100000110100111110010 9
b11000111111011001101101110001111 8
b111 6
b10100 '
#20000
b11101000000000001111010111 "
b11101000000000001111010111 5
b110 $
b110 )
b1100010110010100100111011000101 %
b1100010110010100100111011000101 *
b1110100000000000111101011101000 #
b1110100000000000111101011101000 (
b11101000000000001111010111 ;
b110 >
b1100010110010100100111011000101 =
b1110100000000000111101011101000 <
b11101000000000001111010111 7
b110 :
b1100010110010100100111011000101 9
b1110100000000000111101011101000 8
b1000 6
b10101 '
#21000
b1000111111000101101000010010000 "
b1000111111000101101000010010000 5
b1 $
b1 )
b10110101010110101100000101101 %
b10110101010110101100000101101 *
b1011110100011100010100010111101 #
b1011110100011100010100010111101 (
b1000111111000101101000010010000 ;
b1 >
b10110101010110101100000101101 =
b1011110100011100010100010111101 <
b1000111111000101101000010010000 7
b1 :
b10110101010110101100000101101 9
b1011110100011100010100010111101 8
b1001 6
b10110 '
#22000
b1011000110000001000000010 "
b1011000110000001000000010 5
b10 $
b10 )
b10000101011100111000011100001010 %
b10000101011100111000011100001010 *
b110001111011110110001001100011 #
b110001111011110110001001100011 (
b1011000110000001000000010 ;
b10 >
b10000101011100111000011100001010 =
b110001111011110110001001100011 <
b1011000110000001000000010 7
b10 :
b10000101011100111000011100001010 9
b110001111011110110001001100011 8
b1010 6
b10111 '
#23000
b11010101011111000110010110101010 "
b11010101011111000110010110101010 5
b11 $
b11 )
b11010101011110000100010110101010 %
b11010101011110000100010110101010 *
b10010000011001000010000100100000 #
b10010000011001000010000100100000 (
b11010101011111000110010110101010 ;
b11 >
b11010101011110000100010110101010 =
b10010000011001000010000100100000 <
b11010101011111000110010110101010 7
b11 :
b11010101011110000100010110101010 9
b10010000011001000010000100100000 8
b1011 6
b11000 '
#24000
b1010100101000111111011010101001 "
b1010100101000111111011010101001 5
b0 $
b0 )
b1001100000111011100000010011 %
b1001100000111011100000010011 *
b1001011001000000011111010010110 #
b1001011001000000011111010010110 (
b1010100101000111111011010101001 ;
b0 >
b1001100000111011100000010011 =
b1001011001000000011111010010110 <
b1010100101000111111011010101001 7
b0 :
b1001100000111011100000010011 9
b1001011001000000011111010010110 8
b1100 6
b11001 '
#25000
b10011100001110000000101100111000 "
b10011100001110000000101100111000 5
b100 $
b100 )
b10110101100111111101110101101011 %
b10110101100111111101110101101011 *
b101001101001111101011001010011 #
b101001101001111101011001010011 (
b10011100001110000000101100111000 ;
b100 >
b10110101100111111101110101101011 =
b101001101001111101011001010011 <
b10011100001110000000101100111000 7
b100 :
b10110101100111111101110101101011 9
b101001101001111101011001010011 8
b1101 6
b11010 '
#26000
b11010010100000001000000000000000 "
b11010010100000001000000000000000 5
b101 $
b101 )
b1010111010101100011111010101110 %
b1010111010101100011111010101110 *
b1000101110100101000000010 #
b1000101110100101000000010 (
b11010010100000001000000000000000 ;
b101 >
b1010111010101100011111010101110 =
b1000101110100101000000010 <
b11010010100000001000000000000000 7
b101 :
b1010111010101100011111010101110 9
b1000101110100101000000010 8
b1110 6
b11011 '
#27000
b111110001010111001011001111000 "
b111110001010111001011001111000 5
b10010001100001000100100100100011 %
b10010001100001000100100100100011 *
b1100111110001010111001011001111 #
b1100111110001010111001011001111 (
b111110001010111001011001111000 ;
b10010001100001000100100100100011 =
b1100111110001010111001011001111 <
b111110001010111001011001111000 7
b10010001100001000100100100100011 9
b1100111110001010111001011001111 8
b1111 6
b11100 '
#28000
1!
b0 "
b0 5
b1001 $
b1001 )
b11110001100010100110000111100 %
b11110001100010100110000111100 *
b1100101011100110000101011001010 #
b1100101011100110000101011001010 (
b0 ;
b1001 >
b11110001100010100110000111100 =
b1100101011100110000101011001010 <
b0 7
b1001 :
b11110001100010100110000111100 9
b1100101011100110000101011001010 8
b10000 6
b11101 '
#29000
0!
b1100101111010101101001011001011 "
b1100101111010101101001011001011 5
b100 $
b100 )
b10100000110001001011001101000001 %
b10100000110001001011001101000001 *
b11000101001011100110000110001010 #
b11000101001011100110000110001010 (
b1100101111010101101001011001011 ;
b100 >
b10100000110001001011001101000001 =
b11000101001011100110000110001010 <
b1100101111010101101001011001011 7
b100 :
b10100000110001001011001101000001 9
b11000101001011100110000110001010 8
b10001 6
b11110 '
#30000
1!
b0 "
b0 5
b1001 $
b1001 )
b1000100100010100001001010001001 %
b1000100100010100001001010001001 *
b10111100001000001111001101111000 #
b10111100001000001111001101111000 (
b0 ;
b1001 >
b1000100100010100001001010001001 =
b10111100001000001111001101111000 <
b0 7
b1001 :
b1000100100010100001001010001001 9
b10111100001000001111001101111000 8
b10010 6
b11111 '
#31000
0!
b1 "
b1 5
b1000 $
b1000 )
b11100011010010111111100111000110 %
b11100011010010111111100111000110 *
b11011011000000100110010110110110 #
b11011011000000100110010110110110 (
b1 ;
b1000 >
b11100011010010111111100111000110 =
b11011011000000100110010110110110 <
b1 7
b1000 :
b11100011010010111111100111000110 9
b11011011000000100110010110110110 8
b10011 6
b100000 '
#32000
b11110011100001001101111111100110 "
b11110011100001001101111111100110 5
b0 $
b0 )
b10010101000011111101110100101010 %
b10010101000011111101110100101010 *
b1011110011101010000001010111100 #
b1011110011101010000001010111100 (
b11110011100001001101111111100110 ;
b0 >
b10010101000011111101110100101010 =
b1011110011101010000001010111100 <
b11110011100001001101111111100110 7
b0 :
b10010101000011111101110100101010 9
b1011110011101010000001010111100 8
b10100 6
b100001 '
#33000
b1110001001011110111110011 "
b1110001001011110111110011 5
b110 $
b110 )
b11000010111100100100000110000101 %
b11000010111100100100000110000101 *
b111000100101111011111001110001 #
b111000100101111011111001110001 (
b1110001001011110111110011 ;
b110 >
b11000010111100100100000110000101 =
b111000100101111011111001110001 <
b1110001001011110111110011 7
b110 :
b11000010111100100100000110000101 9
b111000100101111011111001110001 8
b10101 6
b100010 '
#34000
b11101000001000010000000111010 "
b11101000001000010000000111010 5
b10 $
b10 )
b10011101000001100011001100111010 %
b10011101000001100011001100111010 *
b11101110011000110000000111011 #
b11101110011000110000000111011 (
b11101000001000010000000111010 ;
b10 >
b10011101000001100011001100111010 =
b11101110011000110000000111011 <
b11101000001000010000000111010 7
b10 :
b10011101000001100011001100111010 9
b11101110011000110000000111011 8
b10110 6
b100011 '
#35000
b1 "
b1 5
b1001 $
b1001 )
b11111000110110011001101111110001 %
b11111000110110011001101111110001 *
b10001010101010100100101100010101 #
b10001010101010100100101100010101 (
b1 ;
b1001 >
b11111000110110011001101111110001 =
b10001010101010100100101100010101 <
b1 7
b1001 :
b11111000110110011001101111110001 9
b10001010101010100100101100010101 8
b10111 6
b100100 '
#36000
1!
b0 "
b0 5
b1000 $
b1000 )
b10100110001101011111101101001100 %
b10100110001101011111101101001100 *
b10110001001000110000011101100010 #
b10110001001000110000011101100010 (
b0 ;
b1000 >
b10100110001101011111101101001100 =
b10110001001000110000011101100010 <
b0 7
b1000 :
b10100110001101011111101101001100 9
b10110001001000110000011101100010 8
b11000 6
b100101 '
#37000
0!
b11111111111111011010100111111111 "
b11111111111111011010100111111111 5
b11 $
b11 )
b11111100011011011010100111111000 %
b11111100011011011010100111111000 *
b11000111101110011010000110001111 #
b11000111101110011010000110001111 (
b11111111111111011010100111111111 ;
b11 >
b11111100011011011010100111111000 =
b11000111101110011010000110001111 <
b11111111111111011010100111111111 7
b11 :
b11111100011011011010100111111000 9
b11000111101110011010000110001111 8
b11001 6
b100110 '
#38000
b100001010001101100001001000011 "
b100001010001101100001001000011 5
b1 $
b1 )
b101110011111011001010001011100 %
b101110011111011001010001011100 *
b1001111110001000101011010011111 #
b1001111110001000101011010011111 (
b100001010001101100001001000011 ;
b1 >
b101110011111011001010001011100 =
b1001111110001000101011010011111 <
b100001010001101100001001000011 7
b1 :
b101110011111011001010001011100 9
b1001111110001000101011010011111 8
b11010 6
b100111 '
#39000
b11100000011100000000010111000000 "
b11100000011100000000010111000000 5
b100 $
b100 )
b100100101011100011001001001001 %
b100100101011100011001001001001 *
b11000100110111100011011110001001 #
b11000100110111100011011110001001 (
b11100000011100000000010111000000 ;
b100 >
b100100101011100011001001001001 =
b11000100110111100011011110001001 <
b11100000011100000000010111000000 7
b100 :
b100100101011100011001001001001 9
b11000100110111100011011110001001 8
b11011 6
b101000 '
#40000
b11010111111111 "
b11010111111111 5
b111 $
b111 )
b101000110001111111110001010001 %
b101000110001111111110001010001 *
b1101011111111101100000011010111 #
b1101011111111101100000011010111 (
b11010111111111 ;
b111 >
b101000110001111111110001010001 =
b1101011111111101100000011010111 <
b11010111111111 7
b111 :
b101000110001111111110001010001 9
b1101011111111101100000011010111 8
b11100 6
b101001 '
#41000
b1 "
b1 5
b1000 $
b1000 )
b1100001001011001100111011000010 %
b1100001001011001100111011000010 *
b10000110000111010111111100001100 #
b10000110000111010111111100001100 (
b1 ;
b1000 >
b1100001001011001100111011000010 =
b10000110000111010111111100001100 <
b1 7
b1000 :
b1100001001011001100111011000010 9
b10000110000111010111111100001100 8
b11101 6
b101010 '
#42000
b11100000000000000000000000000000 "
b11100000000000000000000000000000 5
b101 $
b101 )
b10011110111100101110110100111101 %
b10011110111100101110110100111101 *
b111011100000100101101001110111 #
b111011100000100101101001110111 (
b11100000000000000000000000000000 ;
b101 >
b10011110111100101110110100111101 =
b111011100000100101101001110111 <
b11100000000000000000000000000000 7
b101 :
b10011110111100101110110100111101 9
b111011100000100101101001110111 8
b11110 6
b101011 '
#43000
b11111100000101000 "
b11111100000101000 5
b110 $
b110 )
b10110110111001011000000101101101 %
b10110110111001011000000101101101 *
b111111000001010000000001111110 #
b111111000001010000000001111110 (
b11111100000101000 ;
b110 >
b10110110111001011000000101101101 =
b111111000001010000000001111110 <
b11111100000101000 7
b110 :
b10110110111001011000000101101101 9
b111111000001010000000001111110 8
b11111 6
b101100 '
#44000
b11111111111111111111000111111010 "
b11111111111111111111000111111010 5
b111 $
b111 )
b1101001111010111111011011010011 %
b1101001111010111111011011010011 *
b10001111110100101000111100011111 #
b10001111110100101000111100011111 (
b11111111111111111111000111111010 ;
b111 >
b1101001111010111111011011010011 =
b10001111110100101000111100011111 <
b11111111111111111111000111111010 7
b111 :
b1101001111010111111011011010011 9
b10001111110100101000111100011111 8
b100000 6
b101101 '
#45000
b111 "
b111 5
b110 $
b110 )
b10101101110110100101100101011011 %
b10101101110110100101100101011011 *
b111100000101001000100001111000 #
b111100000101001000100001111000 (
b111 ;
b110 >
b10101101110110100101100101011011 =
b111100000101001000100001111000 <
b111 7
b110 :
b10101101110110100101100101011011 9
b111100000101001000100001111000 8
b100001 6
b101110 '
#46000
b1111111110010101011 "
b1111111110010101011 5
b10010101000011001010111100101010 %
b10010101000011001010111100101010 *
b11111111100101010111000111111 #
b11111111100101010111000111111 (
b1111111110010101011 ;
b10010101000011001010111100101010 =
b11111111100101010111000111111 <
b1111111110010101011 7
b10010101000011001010111100101010 9
b11111111100101010111000111111 8
b100010 6
b101111 '
#47000
b1000111001111110011110010001110 "
b1000111001111110011110010001110 5
b11 $
b11 )
b1000111000110100000110010001110 %
b1000111000110100000110010001110 *
b1000011001111110011100010000110 #
b1000011001111110011100010000110 (
b1000111001111110011110010001110 ;
b11 >
b1000111000110100000110010001110 =
b1000011001111110011100010000110 <
b1000111001111110011110010001110 7
b11 :
b1000111000110100000110010001110 9
b1000011001111110011100010000110 8
b100011 6
b110000 '
#48000
b11111111111101001101011001100111 "
b11111111111101001101011001100111 5
b111 $
b111 )
b10011011111011011110000100110 %
b10011011111011011110000100110 *
b11111101001101011001100111111010 #
b11111101001101011001100111111010 (
b11111111111101001101011001100111 ;
b111 >
b10011011111011011110000100110 =
b11111101001101011001100111111010 <
b11111111111101001101011001100111 7
b111 :
b10011011111011011110000100110 9
b11111101001101011001100111111010 8
b100100 6
b110001 '
#49000
b1010111100110111011110010101111 "
b1010111100110111011110010101111 5
b11 $
b11 )
b10111100110011010100000101111 %
b10111100110011010100000101111 *
b1010001100010111011010010100011 #
b1010001100010111011010010100011 (
b1010111100110111011110010101111 ;
b11 >
b10111100110011010100000101111 =
b1010001100010111011010010100011 <
b1010111100110111011110010101111 7
b11 :
b10111100110011010100000101111 9
b1010001100010111011010010100011 8
b100101 6
b110010 '
#50000
b1 "
b1 5
b1001 $
b1001 )
b10100010001010010000110101000100 %
b10100010001010010000110101000100 *
b101111110110000101011001011111 #
b101111110110000101011001011111 (
b1 ;
b1001 >
b10100010001010010000110101000100 =
b101111110110000101011001011111 <
b1 7
b1001 :
b10100010001010010000110101000100 9
b101111110110000101011001011111 8
b100110 6
b110011 '
#51000
b1100101100110110011011011 "
b1100101100110110011011011 5
b110 $
b110 )
b1110011000010010001101011100110 %
b1110011000010010001101011100110 *
b1100101100110110011011011001011 #
b1100101100110110011011011001011 (
b1100101100110110011011011 ;
b110 >
b1110011000010010001101011100110 =
b1100101100110110011011011001011 <
b1100101100110110011011011 7
b110 :
b1110011000010010001101011100110 9
b1100101100110110011011011001011 8
b100111 6
b110100 '
#52000
b11100010010011010010001111000100 "
b11100010010011010010001111000100 5
b100 $
b100 )
b1110110100000101110001011101101 %
b1110110100000101110001011101101 *
b10010100110011111100000100101001 #
b10010100110011111100000100101001 (
b11100010010011010010001111000100 ;
b100 >
b1110110100000101110001011101101 =
b10010100110011111100000100101001 <
b11100010010011010010001111000100 7
b100 :
b1110110100000101110001011101101 9
b10010100110011111100000100101001 8
b101000 6
b110101 '
#53000
b1101000000101010101010011010000 "
b1101000000101010101010011010000 5
b1011010100010101110001010110101 %
b1011010100010101110001010110101 *
b110010100111111011011001100101 #
b110010100111111011011001100101 (
b1101000000101010101010011010000 ;
b1011010100010101110001010110101 =
b110010100111111011011001100101 <
b1101000000101010101010011010000 7
b1011010100010101110001010110101 9
b110010100111111011011001100101 8
b101001 6
b110110 '
#54000
b11110110000001110011000111101 "
b11110110000001110011000111101 5
b10100010001100011111111101000100 %
b10100010001100011111111101000100 *
b10111100111100010001100101111001 #
b10111100111100010001100101111001 (
b11110110000001110011000111101 ;
b10100010001100011111111101000100 =
b10111100111100010001100101111001 <
b11110110000001110011000111101 7
b10100010001100011111111101000100 9
b10111100111100010001100101111001 8
b101010 6
b110111 '
#55000
b1001000010110010101000000000000 "
b1001000010110010101000000000000 5
b101 $
b101 )
b11010101111101101010110110101011 %
b11010101111101101010110110101011 *
b10010101000010010000101100101010 #
b10010101000010010000101100101010 (
b1001000010110010101000000000000 ;
b101 >
b11010101111101101010110110101011 =
b10010101000010010000101100101010 <
b1001000010110010101000000000000 7
b101 :
b11010101111101101010110110101011 9
b10010101000010010000101100101010 8
b101011 6
b111000 '
#56000
b10100011000000110001000101000110 "
b10100011000000110001000101000110 5
b100 $
b100 )
b1001101010111101011110010011010 %
b1001101010111101011110010011010 *
b11101110010111011010110111011100 #
b11101110010111011010110111011100 (
b10100011000000110001000101000110 ;
b100 >
b1001101010111101011110010011010 =
b11101110010111011010110111011100 <
b10100011000000110001000101000110 7
b100 :
b1001101010111101011110010011010 9
b11101110010111011010110111011100 8
b101100 6
b111001 '
#57000
b110000111 "
b110000111 5
b110 $
b110 )
b10101011000011101110110101010110 %
b10101011000011101110110101010110 *
b1100001111100010000001011000011 #
b1100001111100010000001011000011 (
b110000111 ;
b110 >
b10101011000011101110110101010110 =
b1100001111100010000001011000011 <
b110000111 7
b110 :
b10101011000011101110110101010110 9
b1100001111100010000001011000011 8
b101101 6
b111010 '
#58000
1!
b0 "
b0 5
b1000 $
b1000 )
b101001100010011010000001010 %
b101001100010011010000001010 *
b110011110110010111011001100111 #
b110011110110010111011001100111 (
b0 ;
b1000 >
b101001100010011010000001010 =
b110011110110010111011001100111 <
b0 7
b1000 :
b101001100010011010000001010 9
b110011110110010111011001100111 8
b101110 6
b111011 '
#59000
0!
b10111100110111111000111101111001 "
b10111100110111111000111101111001 5
b11 $
b11 )
b10111100110100011000011101111001 %
b10111100110100011000011101111001 *
b11100000011101000101000111000 #
b11100000011101000101000111000 (
b10111100110111111000111101111001 ;
b11 >
b10111100110100011000011101111001 =
b11100000011101000101000111000 <
b10111100110111111000111101111001 7
b11 :
b10111100110100011000011101111001 9
b11100000011101000101000111000 8
b101111 6
b111100 '
#60000
b10010100001110110001110100100111 "
b10010100001110110001110100100111 5
b0 $
b0 )
b11001001110001100101110110010011 %
b11001001110001100101110110010011 *
b11001010011101001011111110010100 #
b11001010011101001011111110010100 (
b10010100001110110001110100100111 ;
b0 >
b11001001110001100101110110010011 =
b11001010011101001011111110010100 <
b10010100001110110001110100100111 7
b0 :
b11001001110001100101110110010011 9
b11001010011101001011111110010100 8
b110000 6
b111101 '
#61000
b111110111011000110000001111110 "
b111110111011000110000001111110 5
b1 $
b1 )
b11101101110010110110100111011011 %
b11101101110010110110100111011011 *
b101100101101111100101001011001 #
b101100101101111100101001011001 (
b111110111011000110000001111110 ;
b1 >
b11101101110010110110100111011011 =
b101100101101111100101001011001 <
b111110111011000110000001111110 7
b1 :
b11101101110010110110100111011011 9
b101100101101111100101001011001 8
b110001 6
b111110 '
#62000
b100100101000000010011001001001 "
b100100101000000010011001001001 5
b10 $
b10 )
b110110101001000010011001101101 %
b110110101001000010011001101101 *
b11101100101100001011011111011001 #
b11101100101100001011011111011001 (
b100100101000000010011001001001 ;
b10 >
b110110101001000010011001101101 =
b11101100101100001011011111011001 <
b100100101000000010011001001001 7
b10 :
b110110101001000010011001101101 9
b11101100101100001011011111011001 8
b110010 6
b111111 '
#63000
b11111111111111111111111110010100 "
b11111111111111111111111110010100 5
b111 $
b111 )
b11011011000101110010110110110110 %
b11011011000101110010110110110110 *
b11100101001110110100100111001010 #
b11100101001110110100100111001010 (
b11111111111111111111111110010100 ;
b111 >
b11011011000101110010110110110110 =
b11100101001110110100100111001010 <
b11111111111111111111111110010100 7
b111 :
b11011011000101110010110110110110 9
b11100101001110110100100111001010 8
b110011 6
b1000000 '
#64000
b1 "
b1 5
b1001 $
b1001 )
b10000010011101001001101100000100 %
b10000010011101001001101100000100 *
b100011000001110001101001000110 #
b100011000001110001101001000110 (
b1 ;
b1001 >
b10000010011101001001101100000100 =
b100011000001110001101001000110 <
b1 7
b1001 :
b10000010011101001001101100000100 9
b100011000001110001101001000110 8
b110100 6
b1000001 '
#65000
b11111111111111111111101101001001 "
b11111111111111111111101101001001 5
b111 $
b111 )
b1011010011011101011101010110100 %
b1011010011011101011101010110100 *
b10110100100110000000011101101001 #
b10110100100110000000011101101001 (
b11111111111111111111101101001001 ;
b111 >
b1011010011011101011101010110100 =
b10110100100110000000011101101001 <
b11111111111111111111101101001001 7
b111 :
b1011010011011101011101010110100 9
b10110100100110000000011101101001 8
b110101 6
b1000010 '
